codex_transcripts/__init__.py
codex_transcripts/templates/base.html
codex_transcripts/templates/index.html
codex_transcripts/templates/macros.html
codex_transcripts/templates/page.html
codex_transcripts-0.1.1.dist-info/WHEEL
codex_transcripts-0.1.1.dist-info/entry_points.txt
codex_transcripts-0.1.1.dist-info/METADATA
codex_transcripts-0.1.1.dist-info/RECORD
