Metadata-Version: 2.4
Name: codex-transcripts
Version: 0.1.1
Summary: Convert Codex session files to HTML transcripts
Author: Tim Van Wassenhove
Author-email: Tim Van Wassenhove <github@timvw.be>
License-Expression: Apache-2.0
Requires-Dist: click
Requires-Dist: click-default-group
Requires-Dist: jinja2
Requires-Dist: markdown
Requires-Dist: questionary
Requires-Python: >=3.10
Project-URL: CI, https://github.com/timvw/codex-transcripts/actions
Project-URL: Changelog, https://github.com/timvw/codex-transcripts/releases
Project-URL: Homepage, https://github.com/timvw/codex-transcripts
Project-URL: Issues, https://github.com/timvw/codex-transcripts/issues
